{"0": {"scene": "\u5973\u4e3b\u5bb6\u88e1\u623f\u9593\u4e00", "line": "(\u694a\u627f\u6069\u7ffb\u4e86\u5e7e\u9801\u5b5f\u4ea6\u5b89\u7684\u65e5\u8a18\uff0c\u4e0d\u77e5\u600e\u5730\u8996\u7dda\u537b\u8d8a\u4f86\u8d8a\u6a21\u7cca)", "hazy": true, "source": "res/chapters/1_2/scenes/\u5973\u4e3b\u5bb6\u88e1\u623f\u9593\u4e00\u6726\u6727.jpg"}, "1": {"scene": "\u5973\u4e3b\u5bb6\u88e1\u623f\u9593\u4e00", "line": "\u5b5f\u4ea6\u5b89_\u96e3\u904e:\u300c\u518d\u898b\u4e86\u300d", "hazy": false, "source": "res/chapters/1_2/scenes/\u5973\u4e3b\u5bb6\u88e1\u623f\u9593\u4e00.jpg"}}